note_copy
