Metadata-Version: 2.1
Name: booru-note-copy
Version: 1.0.0
Summary: copy translations between booru-style imageboards
Home-page: https://github.com/torsten-ostgard/booru-note-copy
Author: Torsten Ostgard
License: MIT
Platform: UNKNOWN
Classifier: Environment :: Console
Classifier: Intended Audience :: End Users/Desktop
Classifier: License :: OSI Approved :: MIT License
Classifier: Programming Language :: Python
Classifier: Programming Language :: Python :: 3
Classifier: Programming Language :: Python :: 3.5
Classifier: Programming Language :: Python :: 3.6
Classifier: Programming Language :: Python :: 3.7
Classifier: Operating System :: OS Independent
Classifier: Topic :: Internet
Requires-Python: >=3.5
